README.md
setup.py
negconvert/__init__.py
negconvert/__main__.py
negconvert/contractions.csv
negconvert/negconvert.py
negconvert/opposites.csv
negconvert/synonyms.csv
negconvert.egg-info/PKG-INFO
negconvert.egg-info/SOURCES.txt
negconvert.egg-info/dependency_links.txt
negconvert.egg-info/entry_points.txt
negconvert.egg-info/requires.txt
negconvert.egg-info/top_level.txt