Metadata-Version: 1.2
Name: negconvert
Version: 1.0.2
Summary: A command line application to normalize text from people tweets for further data processing and visualization.
Home-page: https://github.com/litpuvn/flu-shot
Author: dylan salopek,quan nguyen
Author-email: dylan.salopek@ttu.edu,quan.nguyen@ttu.edu
License: UNKNOWN
Platform: UNKNOWN
Requires-Python: >=3
